{"chunk_definitions":[{"row":20,"row_count":1,"visible":true,"expansion_state":0,"options":{"engine":"r","label":"unnamed-chunk-1","dev":"png"},"document_id":"D6F18225","chunk_id":"cgd78m1yrknk3","chunk_label":"unnamed-chunk-1"},{"row":25,"row_count":1,"visible":true,"expansion_state":0,"options":{"engine":"r","label":"unnamed-chunk-2","dev":"png"},"document_id":"D6F18225","chunk_id":"c97qb3d8pyxk6","chunk_label":"unnamed-chunk-2"},{"row":31,"row_count":1,"visible":true,"expansion_state":0,"options":{"engine":"r","label":"unnamed-chunk-5","dev":"png"},"document_id":"D6F18225","chunk_id":"ca1c6zcps0704","chunk_label":"unnamed-chunk-3"},{"row":37,"row_count":1,"visible":true,"expansion_state":0,"options":{"engine":"r","label":"Q2","dev":"png"},"document_id":"D6F18225","chunk_id":"cda1g09qldkby","chunk_label":"Q2"},{"row":46,"row_count":1,"visible":true,"expansion_state":0,"options":{"engine":"r","label":"unnamed-chunk-6","dev":"png"},"document_id":"D6F18225","chunk_id":"c78f17hvf7xu8","chunk_label":"unnamed-chunk-4"},{"row":54,"row_count":1,"visible":true,"expansion_state":0,"options":{"engine":"r","label":"unnamed-chunk-7","dev":"png"},"document_id":"D6F18225","chunk_id":"c9unbdfgwu8pb","chunk_label":"unnamed-chunk-5"},{"row":63,"row_count":1,"visible":true,"expansion_state":0,"options":{"engine":"r","label":"unnamed-chunk-8","dev":"png"},"document_id":"D6F18225","chunk_id":"cjoc0r8gvre85","chunk_label":"unnamed-chunk-6"},{"row":69,"row_count":1,"visible":true,"expansion_state":0,"options":{"engine":"r","label":"unnamed-chunk-9","dev":"png"},"document_id":"D6F18225","chunk_id":"cf8z28nxwq1c4","chunk_label":"unnamed-chunk-7"},{"row":100,"row_count":1,"visible":true,"expansion_state":0,"options":{"engine":"r","label":"unnamed-chunk-4","dev":"png"},"document_id":"D6F18225","chunk_id":"cqd9zdnfwz1cj","chunk_label":"unnamed-chunk-12"},{"row":113,"row_count":1,"visible":true,"expansion_state":0,"options":{"engine":"r","label":"unnamed-chunk-10","dev":"png"},"document_id":"D6F18225","chunk_id":"c3wuznc7mg8v3","chunk_label":"unnamed-chunk-14"},{"row":124,"row_count":1,"visible":true,"expansion_state":0,"options":{"engine":"r","label":"unnamed-chunk-11","dev":"png"},"document_id":"D6F18225","chunk_id":"cnhl7jrxvb174","chunk_label":"unnamed-chunk-15"},{"row":134,"row_count":1,"visible":true,"expansion_state":0,"options":{"engine":"r","label":"unnamed-chunk-12","dev":"png"},"document_id":"D6F18225","chunk_id":"cqcfr8bmnt4oc","chunk_label":"unnamed-chunk-16"},{"row":142,"row_count":1,"visible":true,"expansion_state":0,"options":{"engine":"r","label":"unnamed-chunk-13","dev":"png"},"document_id":"D6F18225","chunk_id":"c5zteo6rnoy5r","chunk_label":"unnamed-chunk-17"},{"row":152,"row_count":1,"visible":true,"expansion_state":0,"options":{"engine":"r","label":"unnamed-chunk-14","dev":"png"},"document_id":"D6F18225","chunk_id":"caf6kclchhk9n","chunk_label":"unnamed-chunk-18"},{"row":158,"row_count":1,"visible":true,"expansion_state":0,"options":{"engine":"r","label":"unnamed-chunk-15","dev":"png"},"document_id":"D6F18225","chunk_id":"c26z0k3xcelag","chunk_label":"unnamed-chunk-19"},{"row":165,"row_count":1,"visible":true,"expansion_state":0,"options":{"engine":"r","label":"unnamed-chunk-16","dev":"png"},"document_id":"D6F18225","chunk_id":"cn4yqti2k94bf","chunk_label":"unnamed-chunk-20"},{"row":197,"row_count":1,"visible":true,"expansion_state":0,"options":{"engine":"r","label":"unnamed-chunk-3","dev":"png"},"document_id":"D6F18225","chunk_id":"cekfglgeugg17","chunk_label":"unnamed-chunk-23"}],"doc_write_time":1723712052}